{
  "updated_at": "2026-05-19T00:07:50.081Z",
  "jp": {
    "total": [
      "俺だけレベルMAXなビギナー",
      "枯れた花に涙を",
      "あなたがしてくれなくても",
      "地味妻のヒミツ",
      "隣の席のエンジニアさんが転職したいようです。",
      "幼馴染コンプレックス",
      "藤堂司の恋愛事情",
      "どうやら私、大公妃が天職みたいです",
      "怪力乱神～血に染まった本性～",
      "オークの樹の下",
      "神血の救世主～0.00000001%を引き当て最強へ～",
      "万能女中コニー・ヴィレ【単話売】",
      "クズ夫の子供になって復讐します（連載版）",
      "転生したらバーバリアンになった",
      "問題な王子様",
      "楽園に宿る影",
      "もふもふとむくむくと異世界漂流生活 ～おいしいごはん、かみさま、かぞく付き～",
      "聖女じゃなかったので、王宮でのんびりご飯を作ることにしました【分冊版】",
      "黒幕の公爵が契約結婚を提案しました",
      "御社の不倫の件～絶対に別れさせます～",
      "TSUYOSHI 誰も勝てない、アイツには",
      "鉄槌教師",
      "復讐の剣は甘き蜜に溺れる",
      "戦利品の公爵夫人",
      "無自覚聖女は今日も無意識に力を垂れ流す ～公爵家の落ちこぼれ令嬢、嫁ぎ先で幸せを掴み取る～",
      "華麗に離縁してみせますわ！",
      "あなたに愛されなくても結構です",
      "放っておけない関係",
      "公爵家の男たちに溺愛されて離婚できません！",
      "末っ子皇女殿下"
    ],
    "male": [
      "俺だけレベルMAXなビギナー",
      "あなたがしてくれなくても",
      "隣の席のエンジニアさんが転職したいようです。",
      "怪力乱神～血に染まった本性～",
      "神血の救世主～0.00000001%を引き当て最強へ～",
      "転生したらバーバリアンになった",
      "TSUYOSHI 誰も勝てない、アイツには",
      "鉄槌教師",
      "コードネーム：バッドロー",
      "小悪魔教師サイコ【タテヨミ】",
      "真なる男",
      "部長K",
      "ナノ魔神",
      "強化レベル99 木の棒",
      "キングダム",
      "外見至上主義",
      "史上最高の領地設計士",
      "滅亡した家門の回帰者",
      "フォグランド",
      "星剣のソードマスター",
      "転生したら最強すぎるのでモブキャラ演じます",
      "入学傭兵",
      "異世界召喚おじさんの銃無双ライフ ～サバゲー好きサラリーマンは会社終わりに異世界へ直帰する～",
      "レベルガチャ～ハズレステータス『運』が結局一番重要だった件～@COMIC",
      "ダンジョンの幼なじみ【分冊版】",
      "2周目冒険者は隠しクラス〈重力使い〉で最強を目指す",
      "片田舎のおっさん、剣聖になる～ただの田舎の剣術師範だったのに、大成した弟子たちが俺を放ってくれない件～（タテヨミフルカラー版）",
      "課長は今日も定時で帰る",
      "雑用付与術師が自分の最強に気付くまで（コミック）",
      "【単話】復讐の同窓会"
    ],
    "female": [
      "枯れた花に涙を",
      "地味妻のヒミツ",
      "幼馴染コンプレックス",
      "藤堂司の恋愛事情",
      "どうやら私、大公妃が天職みたいです",
      "オークの樹の下",
      "万能女中コニー・ヴィレ【単話売】",
      "クズ夫の子供になって復讐します（連載版）",
      "問題な王子様",
      "楽園に宿る影",
      "もふもふとむくむくと異世界漂流生活 ～おいしいごはん、かみさま、かぞく付き～",
      "聖女じゃなかったので、王宮でのんびりご飯を作ることにしました【分冊版】",
      "黒幕の公爵が契約結婚を提案しました",
      "御社の不倫の件～絶対に別れさせます～",
      "復讐の剣は甘き蜜に溺れる",
      "戦利品の公爵夫人",
      "無自覚聖女は今日も無意識に力を垂れ流す ～公爵家の落ちこぼれ令嬢、嫁ぎ先で幸せを掴み取る～",
      "華麗に離縁してみせますわ！",
      "あなたに愛されなくても結構です",
      "放っておけない関係",
      "公爵家の男たちに溺愛されて離婚できません！",
      "末っ子皇女殿下",
      "帝国一の悪女に溺愛がとまりません！",
      "葡萄が実る前に",
      "聖女だけど闇堕ちしたらひよこになりました！@COMIC",
      "目覚めたら＃ビジュ爆発してました",
      "君に似た子",
      "脱いだら絶倫!?身体の相性で結ぶ契約婚",
      "今世は喜んで夫をお譲りします",
      "顔が良すぎる上司に「契約恋愛」を強いられました！？"
    ]
  }
}